LICENSE
MANIFEST.in
README.rst
setup.py
candv/__init__.py
candv/_utils.py
candv/core.py
candv/exceptions.py
candv/ext.py
candv/version.py
candv.egg-info/PKG-INFO
candv.egg-info/SOURCES.txt
candv.egg-info/dependency_links.txt
candv.egg-info/top_level.txt
candv.egg-info/zip-safe
requirements/test.txt