Metadata-Version: 2.1
Name: candv
Version: 1.5.0
Summary: Constants and Values: create enum-like complext constants with the ability to attach arbitrary attributes to them, e.g. values, human-readable names, help texts and so on
Home-page: https://github.com/oblalex/candv/tree/v1.5.0
Author: Oleksandr Oblovatnyi
Author-email: oblovatniy@gmail.com
License: MIT
Keywords: constants,values,structures,choices,enum
Platform: UNKNOWN
Classifier: Development Status :: 5 - Production/Stable
Classifier: Intended Audience :: Developers
Classifier: License :: OSI Approved :: MIT License
Classifier: Natural Language :: English
Classifier: Operating System :: MacOS :: MacOS X
Classifier: Operating System :: Microsoft :: Windows
Classifier: Operating System :: POSIX
Classifier: Programming Language :: Python :: 3
Classifier: Topic :: Software Development :: Libraries
Requires-Python: >=3.7
